LICENSE
README.md
setup.py
NlpToolkit_WordNet_Cy.egg-info/PKG-INFO
NlpToolkit_WordNet_Cy.egg-info/SOURCES.txt
NlpToolkit_WordNet_Cy.egg-info/dependency_links.txt
NlpToolkit_WordNet_Cy.egg-info/requires.txt
NlpToolkit_WordNet_Cy.egg-info/top_level.txt
WordNet/CategoryType.py
WordNet/IdMapping.c
WordNet/IdMapping.pyx
WordNet/InterlingualDependencyType.py
WordNet/InterlingualRelation.c
WordNet/InterlingualRelation.pxd
WordNet/InterlingualRelation.pyx
WordNet/Literal.c
WordNet/Literal.pxd
WordNet/Literal.pyx
WordNet/Relation.c
WordNet/Relation.pxd
WordNet/Relation.pyx
WordNet/SemanticRelation.c
WordNet/SemanticRelation.pxd
WordNet/SemanticRelation.pyx
WordNet/SemanticRelationType.py
WordNet/SynSet.c
WordNet/SynSet.pxd
WordNet/SynSet.pyx
WordNet/Synonym.c
WordNet/Synonym.pxd
WordNet/Synonym.pyx
WordNet/WordNet.c
WordNet/WordNet.pxd
WordNet/WordNet.pyx
WordNet/__init__.py
WordNet/Similarity/ICSimilarity.c
WordNet/Similarity/ICSimilarity.pxd
WordNet/Similarity/ICSimilarity.pyx
WordNet/Similarity/JCN.c
WordNet/Similarity/JCN.pyx
WordNet/Similarity/LCH.c
WordNet/Similarity/LCH.pyx
WordNet/Similarity/Lin.c
WordNet/Similarity/Lin.pyx
WordNet/Similarity/Resnik.c
WordNet/Similarity/Resnik.pyx
WordNet/Similarity/Similarity.c
WordNet/Similarity/Similarity.pxd
WordNet/Similarity/Similarity.pyx
WordNet/Similarity/SimilarityPath.c
WordNet/Similarity/SimilarityPath.pyx
WordNet/Similarity/WuPalmer.c
WordNet/Similarity/WuPalmer.pyx
WordNet/Similarity/__init__.py
WordNet/data/__init__.py
WordNet/data/english_exception.xml
WordNet/data/english_wordnet_version_31.xml
WordNet/data/turkish_wordnet.xml
nlptoolkit_wordnet_cy.egg-info/PKG-INFO
nlptoolkit_wordnet_cy.egg-info/SOURCES.txt
nlptoolkit_wordnet_cy.egg-info/dependency_links.txt
nlptoolkit_wordnet_cy.egg-info/requires.txt
nlptoolkit_wordnet_cy.egg-info/top_level.txt