Metadata-Version: 2.4
Name: nlptoolkit-wordnet-cy
Version: 1.0.14
Summary: Turkish WordNet KeNet
Home-page: https://github.com/StarlangSoftware/TurkishWordNet-Cy
Author: olcay
Author-email: olcay.yildiz@ozyegin.edu.tr
License-File: LICENSE
Requires-Dist: NlpToolkit-MorphologicalAnalysis-Cy
Dynamic: author
Dynamic: author-email
Dynamic: description
Dynamic: description-content-type
Dynamic: home-page
Dynamic: license-file
Dynamic: requires-dist
Dynamic: summary
